ttb/__init__.py
ttb/callback.py
Tensorflow_Telegram_Bot-0.0.2.dist-info/METADATA
Tensorflow_Telegram_Bot-0.0.2.dist-info/WHEEL
Tensorflow_Telegram_Bot-0.0.2.dist-info/top_level.txt
Tensorflow_Telegram_Bot-0.0.2.dist-info/RECORD
