Metadata-Version: 2.1
Name: Tensorflow-Telegram-Bot
Version: 0.0.2
Summary: TensorFlow Telegram Bot which can be used as callback
Home-page: https://github.com/Yeachan-Heo/Tensorflow-Telegram-Bot.git
Author: Yeachan-Heo
Author-email: hurrc04@gmail.com
License: MIT
Platform: UNKNOWN
